Metadata-Version: 1.1
Name: django-scraoy
Version: 0.1a1
Summary: apis for you can use scrapy in django
Home-page: https://github.com/youngershen/django-scrapy
Author: younger shen
Author-email: younger.x.shen@gmail.com
License: MIT
Keywords: django-ueditor-plugin,django,ueditor
Platform: UNKNOWN
Classifier: Development Status :: 2 - Pre-Alpha
Classifier: Environment :: Web Environment
Classifier: Framework :: Django
Classifier: Intended Audience :: Developers
Classifier: License :: OSI Approved :: MIT License
Classifier: Natural Language :: English
Classifier: Programming Language :: Python :: 2.7
